<mxfile host="app.diagrams.net" agent="Mozilla/5.0 (X11; Ubuntu; Linux x86_64; rv:146.0) Gecko/20100101 Firefox/146.0" version="29.2.9">
  <diagram name="Page-1" id="xBDgK7sUF1FwoECa91p5">
    <mxGraphModel dx="2968" dy="1960" grid="1" gridSize="10" guides="1" tooltips="1" connect="1" arrows="1" fold="1" page="1" pageScale="1" pageWidth="850" pageHeight="1100" math="0" shadow="0">
      <root>
        <mxCell id="0" />
        <mxCell id="1" parent="0" />
        <mxCell id="8f4O_Xt_eh_mQ_HBJD7Y-1" parent="1" style="verticalAlign=top;align=left;overflow=fill;fontSize=12;fontFamily=Helvetica;html=1;fillColor=#ffffff;strokeColor=#000000;" value="&lt;p style=&quot;margin: 4px 0px 0px; text-align: center; text-decoration: underline;&quot;&gt;&lt;font style=&quot;font-size: 13px&quot;&gt;&lt;b&gt;Proposal&lt;/b&gt;&lt;br&gt;&lt;/font&gt;&lt;/p&gt;&lt;hr&gt;" vertex="1">
          <mxGeometry height="82" width="147" x="600" y="91.5" as="geometry" />
        </mxCell>
        <mxCell id="8f4O_Xt_eh_mQ_HBJD7Y-2" parent="1" style="verticalAlign=top;align=left;overflow=fill;fontSize=12;fontFamily=Helvetica;html=1;fillColor=#eeeeee;strokeColor=#36393d;dashed=1;" value="&lt;p style=&quot;margin: 4px 0px 0px; text-align: center; text-decoration: underline;&quot;&gt;&lt;font style=&quot;font-size: 13px&quot;&gt;&lt;b&gt;ProposedTo&lt;/b&gt;&lt;br&gt;&lt;/font&gt;&lt;/p&gt;&lt;hr&gt;&lt;p style=&quot;margin: 0px ; margin-left: 8px&quot;&gt;&lt;br&gt;&lt;/p&gt;" vertex="1">
          <mxGeometry height="46" width="125" x="700" y="219.5" as="geometry" />
        </mxCell>
        <mxCell id="8f4O_Xt_eh_mQ_HBJD7Y-3" edge="1" parent="1" source="8f4O_Xt_eh_mQ_HBJD7Y-2" style="endArrow=classic;html=1;exitX=0.25;exitY=0;exitDx=0;exitDy=0;entryX=0.75;entryY=1;entryDx=0;entryDy=0;labelBackgroundColor=none;dashed=1;" target="8f4O_Xt_eh_mQ_HBJD7Y-1" value="proposed">
          <mxGeometry height="50" relative="1" width="50" x="-0.0049" y="-12" as="geometry">
            <mxPoint as="offset" />
            <mxPoint x="360" y="206.5" as="sourcePoint" />
            <mxPoint x="410" y="156.5" as="targetPoint" />
          </mxGeometry>
        </mxCell>
        <mxCell id="8f4O_Xt_eh_mQ_HBJD7Y-4" edge="1" parent="1" source="8f4O_Xt_eh_mQ_HBJD7Y-2" style="endArrow=classic;html=1;exitX=0.25;exitY=1;exitDx=0;exitDy=0;entryX=0.75;entryY=0;entryDx=0;entryDy=0;labelBackgroundColor=none;dashed=1;" target="8f4O_Xt_eh_mQ_HBJD7Y-5" value="proposedTo">
          <mxGeometry height="50" relative="1" width="50" as="geometry">
            <Array as="points" />
            <mxPoint x="1760" y="106.5" as="sourcePoint" />
            <mxPoint x="2061.5" y="614.5" as="targetPoint" />
          </mxGeometry>
        </mxCell>
        <mxCell id="8f4O_Xt_eh_mQ_HBJD7Y-5" parent="1" style="verticalAlign=top;align=left;overflow=fill;fontSize=12;fontFamily=Helvetica;html=1;fillColor=#ffffff;strokeColor=#000000;" value="&lt;p style=&quot;margin: 4px 0px 0px; text-align: center; text-decoration: underline;&quot;&gt;&lt;font style=&quot;font-size: 13px&quot;&gt;&lt;b&gt;Agent&lt;/b&gt;&lt;br&gt;&lt;/font&gt;&lt;/p&gt;&lt;hr&gt;&amp;nbsp; &lt;font style=&quot;font-size: 11px&quot;&gt;&lt;br&gt;&lt;/font&gt;" vertex="1">
          <mxGeometry height="65" width="120" x="600" y="306.5" as="geometry" />
        </mxCell>
        <mxCell id="8f4O_Xt_eh_mQ_HBJD7Y-6" edge="1" parent="1" source="8f4O_Xt_eh_mQ_HBJD7Y-1" style="endArrow=classic;html=1;rounded=1;exitX=0.25;exitY=1;exitDx=0;exitDy=0;entryX=0.25;entryY=0;entryDx=0;entryDy=0;labelBackgroundColor=none;" target="8f4O_Xt_eh_mQ_HBJD7Y-5" value="proposedTo">
          <mxGeometry height="50" relative="1" width="50" x="0.3311" y="-10" as="geometry">
            <mxPoint y="1" as="offset" />
            <Array as="points" />
            <mxPoint x="710" y="216.5" as="sourcePoint" />
            <mxPoint x="760" y="166.5" as="targetPoint" />
          </mxGeometry>
        </mxCell>
        <mxCell id="8f4O_Xt_eh_mQ_HBJD7Y-12" parent="1" style="verticalAlign=top;align=left;overflow=fill;fontSize=12;fontFamily=Helvetica;html=1;fillColor=#ffffff;strokeColor=#000000;" value="&lt;p style=&quot;margin: 4px 0px 0px; text-align: center; text-decoration: underline;&quot;&gt;&lt;font style=&quot;font-size: 13px&quot;&gt;&lt;b&gt;Intent&lt;/b&gt;&lt;br&gt;&lt;/font&gt;&lt;/p&gt;&lt;hr&gt;&lt;br&gt;&lt;p style=&quot;margin: 0px ; margin-left: 8px&quot;&gt;&lt;font&gt;&lt;br&gt;&lt;/font&gt;&lt;/p&gt;" vertex="1">
          <mxGeometry height="70" width="168" x="66" y="220" as="geometry" />
        </mxCell>
        <mxCell id="8f4O_Xt_eh_mQ_HBJD7Y-13" parent="1" style="verticalAlign=top;align=left;overflow=fill;fontSize=12;fontFamily=Helvetica;html=1;fillColor=#ffffff;strokeColor=#000000;" value="&lt;p style=&quot;margin: 4px 0px 0px; text-align: center; text-decoration: underline;&quot;&gt;&lt;font style=&quot;font-size: 13px&quot;&gt;&lt;b&gt;Proposal&lt;/b&gt;&lt;br&gt;&lt;/font&gt;&lt;/p&gt;&lt;hr&gt;" vertex="1">
          <mxGeometry height="77" width="147" x="370" y="91.5" as="geometry" />
        </mxCell>
        <mxCell id="8f4O_Xt_eh_mQ_HBJD7Y-14" parent="1" style="verticalAlign=top;align=left;overflow=fill;fontSize=12;fontFamily=Helvetica;html=1;fillColor=#eeeeee;strokeColor=#36393d;dashed=1;" value="&lt;p style=&quot;margin: 4px 0px 0px; text-align: center; text-decoration: underline;&quot;&gt;&lt;font style=&quot;font-size: 13px&quot;&gt;&lt;b&gt;ProposedIntent&lt;/b&gt;&lt;br&gt;&lt;/font&gt;&lt;/p&gt;&lt;hr&gt;&lt;p style=&quot;margin: 0px ; margin-left: 8px&quot;&gt;&lt;br&gt;&lt;/p&gt;" vertex="1">
          <mxGeometry height="60" width="150" x="106" y="100" as="geometry" />
        </mxCell>
        <mxCell id="8f4O_Xt_eh_mQ_HBJD7Y-15" edge="1" parent="1" source="8f4O_Xt_eh_mQ_HBJD7Y-14" style="endArrow=classic;html=1;exitX=1;exitY=0.5;exitDx=0;exitDy=0;entryX=0;entryY=0.25;entryDx=0;entryDy=0;labelBackgroundColor=none;dashed=1;" target="8f4O_Xt_eh_mQ_HBJD7Y-13" value="publishedIn">
          <mxGeometry height="50" relative="1" width="50" x="0.0498" y="-1" as="geometry">
            <mxPoint as="offset" />
            <mxPoint x="108" y="45" as="sourcePoint" />
            <mxPoint x="62" y="40" as="targetPoint" />
          </mxGeometry>
        </mxCell>
        <mxCell id="8f4O_Xt_eh_mQ_HBJD7Y-16" edge="1" parent="1" source="8f4O_Xt_eh_mQ_HBJD7Y-14" style="endArrow=classic;html=1;exitX=0.5;exitY=1;exitDx=0;exitDy=0;entryX=0.5;entryY=0;entryDx=0;entryDy=0;labelBackgroundColor=none;dashed=1;" target="8f4O_Xt_eh_mQ_HBJD7Y-12" value="publishes">
          <mxGeometry height="50" relative="1" width="50" x="0.1752" y="-11" as="geometry">
            <mxPoint y="1" as="offset" />
            <mxPoint x="8" y="145" as="sourcePoint" />
            <mxPoint x="75.35199999999986" y="167.73000000000002" as="targetPoint" />
          </mxGeometry>
        </mxCell>
        <mxCell id="8f4O_Xt_eh_mQ_HBJD7Y-17" edge="1" parent="1" source="8f4O_Xt_eh_mQ_HBJD7Y-14" style="endArrow=classic;html=1;rounded=0;exitX=0.75;exitY=1;exitDx=0;exitDy=0;entryX=0.75;entryY=0;entryDx=0;entryDy=0;labelBackgroundColor=none;dashed=1;" target="8f4O_Xt_eh_mQ_HBJD7Y-12" value="reciprocal">
          <mxGeometry height="50" relative="1" width="50" x="-0.4806" y="3" as="geometry">
            <mxPoint as="offset" />
            <mxPoint x="130" y="70" as="sourcePoint" />
            <mxPoint x="180" y="20" as="targetPoint" />
          </mxGeometry>
        </mxCell>
        <mxCell id="8f4O_Xt_eh_mQ_HBJD7Y-18" edge="1" parent="1" source="8f4O_Xt_eh_mQ_HBJD7Y-13" style="endArrow=classic;html=1;rounded=1;exitX=0;exitY=0.5;exitDx=0;exitDy=0;entryX=0;entryY=1;entryDx=0;entryDy=0;labelBackgroundColor=none;" target="8f4O_Xt_eh_mQ_HBJD7Y-34" value="publishes">
          <mxGeometry height="50" relative="1" width="50" x="0.4469" y="-11" as="geometry">
            <mxPoint x="-1" as="offset" />
            <Array as="points" />
            <mxPoint x="512" y="102" as="sourcePoint" />
            <mxPoint x="2193" y="649" as="targetPoint" />
          </mxGeometry>
        </mxCell>
        <mxCell id="8f4O_Xt_eh_mQ_HBJD7Y-19" edge="1" parent="1" source="8f4O_Xt_eh_mQ_HBJD7Y-13" style="endArrow=classic;html=1;rounded=1;exitX=0;exitY=0.75;exitDx=0;exitDy=0;entryX=1;entryY=0.714;entryDx=0;entryDy=0;labelBackgroundColor=none;entryPerimeter=0;" target="8f4O_Xt_eh_mQ_HBJD7Y-12" value="reciprocal">
          <mxGeometry height="50" relative="1" width="50" x="0.22" y="14" as="geometry">
            <mxPoint y="1" as="offset" />
            <Array as="points" />
            <mxPoint x="365" y="140" as="sourcePoint" />
            <mxPoint x="244" y="261" as="targetPoint" />
          </mxGeometry>
        </mxCell>
        <mxCell id="8f4O_Xt_eh_mQ_HBJD7Y-20" parent="1" style="verticalAlign=top;align=left;overflow=fill;fontSize=12;fontFamily=Helvetica;html=1;fillColor=#ffffff;strokeColor=#000000;" value="&lt;p style=&quot;margin: 4px 0px 0px; text-align: center; text-decoration: underline;&quot;&gt;&lt;font style=&quot;font-size: 13px&quot;&gt;&lt;b&gt;Commitment&lt;/b&gt;&lt;br&gt;&lt;/font&gt;&lt;/p&gt;&lt;hr&gt;" vertex="1">
          <mxGeometry height="70" width="151" x="229.5" y="920" as="geometry" />
        </mxCell>
        <mxCell id="8f4O_Xt_eh_mQ_HBJD7Y-21" parent="1" style="verticalAlign=top;align=left;overflow=fill;fontSize=12;fontFamily=Helvetica;html=1;fillColor=#ffffff;strokeColor=#000000;" value="&lt;p style=&quot;margin: 4px 0px 0px; text-align: center; text-decoration: underline;&quot;&gt;&lt;font style=&quot;font-size: 13px&quot;&gt;&lt;b&gt;Process&lt;/b&gt;&lt;br&gt;&lt;/font&gt;&lt;/p&gt;&lt;hr&gt;" vertex="1">
          <mxGeometry height="70" width="130" x="240" y="730" as="geometry" />
        </mxCell>
        <mxCell id="8f4O_Xt_eh_mQ_HBJD7Y-22" edge="1" parent="1" source="8f4O_Xt_eh_mQ_HBJD7Y-20" style="endArrow=block;endFill=1;endSize=6;html=1;strokeColor=#000000;exitX=0.25;exitY=0;entryX=0.25;entryY=1;labelBackgroundColor=none;entryDx=0;entryDy=0;exitDx=0;exitDy=0;startArrow=classic;startFill=1;" target="8f4O_Xt_eh_mQ_HBJD7Y-21" value="inputOf">
          <mxGeometry width="100" as="geometry">
            <mxPoint x="-10" y="-30" as="offset" />
            <mxPoint x="119" y="683" as="sourcePoint" />
            <mxPoint x="34.666666666666515" y="896" as="targetPoint" />
          </mxGeometry>
        </mxCell>
        <mxCell id="8f4O_Xt_eh_mQ_HBJD7Y-23" edge="1" parent="1" source="8f4O_Xt_eh_mQ_HBJD7Y-20" style="endArrow=block;endFill=1;endSize=6;html=1;exitX=0.75;exitY=0;entryX=0.75;entryY=1;labelBackgroundColor=none;entryDx=0;entryDy=0;exitDx=0;exitDy=0;startArrow=classic;startFill=1;" target="8f4O_Xt_eh_mQ_HBJD7Y-21" value="outputOf">
          <mxGeometry width="100" as="geometry">
            <mxPoint x="-3" y="-30" as="offset" />
            <mxPoint x="373" y="723" as="sourcePoint" />
            <mxPoint x="9" y="891" as="targetPoint" />
          </mxGeometry>
        </mxCell>
        <mxCell id="8f4O_Xt_eh_mQ_HBJD7Y-24" parent="1" style="text;html=1;strokeColor=none;fillColor=none;align=center;verticalAlign=middle;whiteSpace=wrap;rounded=0;" value="&lt;font style=&quot;font-size: 11px;&quot;&gt;hasInput *&lt;/font&gt;" vertex="1">
          <mxGeometry height="30" width="76" x="202" y="895" as="geometry" />
        </mxCell>
        <mxCell id="8f4O_Xt_eh_mQ_HBJD7Y-25" parent="1" style="text;html=1;strokeColor=none;fillColor=none;align=center;verticalAlign=middle;whiteSpace=wrap;rounded=0;" value="*&amp;nbsp;&lt;font style=&quot;font-size: 11px;&quot;&gt;hasOutput&lt;br&gt;&lt;/font&gt;" vertex="1">
          <mxGeometry height="30" width="74" x="341" y="897" as="geometry" />
        </mxCell>
        <mxCell id="8f4O_Xt_eh_mQ_HBJD7Y-27" parent="1" style="verticalAlign=top;align=left;overflow=fill;fontSize=12;fontFamily=Helvetica;html=1;fillColor=#ffffff;strokeColor=#000000;" value="&lt;p style=&quot;margin: 0px ; margin-top: 4px ; text-align: center ; text-decoration: underline&quot;&gt;&lt;font style=&quot;font-size: 13px&quot;&gt;&lt;b&gt;vf:Intent&lt;/b&gt;&lt;br&gt;&lt;/font&gt;&lt;/p&gt;&lt;hr&gt;&lt;p style=&quot;margin: 0px ; margin-left: 8px&quot;&gt;&lt;font style=&quot;font-size: 11px&quot;&gt;vf:name&lt;/font&gt;&lt;/p&gt;&lt;p style=&quot;margin: 0px ; margin-left: 8px&quot;&gt;&lt;font style=&quot;font-size: 11px&quot;&gt;vf:resourceQuantity&lt;/font&gt;&lt;/p&gt;&lt;p style=&quot;margin: 0px ; margin-left: 8px&quot;&gt;&lt;font style=&quot;font-size: 11px&quot;&gt;vf:effortQuantity&lt;/font&gt;&lt;/p&gt;&lt;p style=&quot;margin: 0px ; margin-left: 8px&quot;&gt;&lt;font style=&quot;font-size: 11px&quot;&gt;vf:availableQuantity&lt;br&gt;&lt;/font&gt;&lt;/p&gt;&lt;p style=&quot;margin: 0px ; margin-left: 8px&quot;&gt;&lt;font style=&quot;font-size: 11px&quot;&gt;vf:resourceClassifiedAs&lt;br&gt;&lt;/font&gt;&lt;/p&gt;&lt;p style=&quot;margin: 0px ; margin-left: 8px&quot;&gt;&lt;font style=&quot;font-size: 11px&quot;&gt;vf:hasBeginning&lt;/font&gt;&lt;/p&gt;&lt;p style=&quot;margin: 0px ; margin-left: 8px&quot;&gt;&lt;font style=&quot;font-size: 11px&quot;&gt;vf:hasEnd&lt;/font&gt;&lt;/p&gt;&lt;p style=&quot;margin: 0px ; margin-left: 8px&quot;&gt;&lt;font style=&quot;font-size: 11px&quot;&gt;vf:hasPointInTime&lt;br&gt;&lt;/font&gt;&lt;/p&gt;&lt;p style=&quot;margin: 0px ; margin-left: 8px&quot;&gt;&lt;font style=&quot;font-size: 11px&quot;&gt;vf:due&lt;/font&gt;&lt;br&gt;&lt;/p&gt;&lt;p style=&quot;margin: 0px ; margin-left: 8px&quot;&gt;&lt;font style=&quot;font-size: 11px&quot;&gt;vf:inScopeOf&lt;/font&gt;&lt;/p&gt;&lt;p style=&quot;margin: 0px ; margin-left: 8px&quot;&gt;&lt;font style=&quot;font-size: 11px&quot;&gt;vf:finished&lt;br&gt;&lt;/font&gt;&lt;/p&gt;&lt;p style=&quot;margin: 0px ; margin-left: 8px&quot;&gt;&lt;font style=&quot;font-size: 11px&quot;&gt;skos:note&lt;/font&gt;&lt;/p&gt;&lt;p style=&quot;margin: 0px ; margin-left: 8px&quot;&gt;&lt;font style=&quot;font-size: 11px&quot;&gt;vf:image&lt;/font&gt;&lt;/p&gt;&lt;p style=&quot;margin: 0px ; margin-left: 8px&quot;&gt;&lt;font style=&quot;font-size: 11px&quot;&gt;vf:agreedIn&lt;br&gt;&lt;/font&gt;&lt;/p&gt;&lt;p style=&quot;margin: 0px ; margin-left: 8px&quot;&gt;&lt;font style=&quot;font-size: 11px&quot;&gt;vf:atLocation&lt;br&gt;&lt;/font&gt;&lt;/p&gt;&lt;p style=&quot;margin: 0px ; margin-left: 8px&quot;&gt;&lt;font&gt;&lt;br&gt;&lt;/font&gt;&lt;/p&gt;" vertex="1">
          <mxGeometry height="266" width="168" x="980" y="221" as="geometry" />
        </mxCell>
        <mxCell id="8f4O_Xt_eh_mQ_HBJD7Y-28" parent="1" style="verticalAlign=top;align=left;overflow=fill;fontSize=12;fontFamily=Helvetica;html=1;fillColor=#ffffff;strokeColor=#000000;" value="&lt;p style=&quot;margin: 0px ; margin-top: 4px ; text-align: center ; text-decoration: underline&quot;&gt;&lt;font style=&quot;font-size: 13px&quot;&gt;&lt;b&gt;vf:Proposal&lt;/b&gt;&lt;br&gt;&lt;/font&gt;&lt;/p&gt;&lt;hr&gt;&lt;p style=&quot;margin: 0px ; margin-left: 8px&quot;&gt;&lt;font style=&quot;font-size: 11px&quot;&gt;vf:name&lt;/font&gt;&lt;/p&gt;&lt;p style=&quot;margin: 0px 0px 0px 8px ; font-size: 11px&quot;&gt;&lt;font style=&quot;font-size: 11px&quot;&gt;vf:hasBeginning&lt;/font&gt;&lt;/p&gt;&lt;p style=&quot;margin: 0px 0px 0px 8px ; font-size: 11px&quot;&gt;&lt;font style=&quot;font-size: 11px&quot;&gt;vf:hasEnd&lt;/font&gt;&lt;/p&gt;&lt;p style=&quot;margin: 0px 0px 0px 8px ; font-size: 11px&quot;&gt;&lt;font style=&quot;font-size: 11px&quot;&gt;vf:eligibleLocation&lt;br&gt;&lt;/font&gt;&lt;/p&gt;&lt;p style=&quot;margin: 0px 0px 0px 8px ; font-size: 11px&quot;&gt;&lt;font style=&quot;font-size: 11px&quot;&gt;vf:inScopeOf&lt;/font&gt;&lt;/p&gt;&lt;p style=&quot;margin: 0px 0px 0px 8px ; font-size: 11px&quot;&gt;&lt;font style=&quot;font-size: 11px&quot;&gt;vf:unitBased&lt;/font&gt;&lt;br&gt;&lt;/p&gt;&lt;p style=&quot;margin: 0px ; margin-left: 8px&quot;&gt;&lt;font style=&quot;font-size: 11px&quot;&gt;skos:note&lt;/font&gt;&lt;/p&gt;&lt;p style=&quot;margin: 0px ; margin-left: 8px&quot;&gt;&lt;font style=&quot;font-size: 11px&quot;&gt;dcterms:created&lt;br&gt;&lt;/font&gt;&lt;/p&gt;" vertex="1">
          <mxGeometry height="154" width="147" x="1269" y="40" as="geometry" />
        </mxCell>
        <mxCell id="8f4O_Xt_eh_mQ_HBJD7Y-29" parent="1" style="verticalAlign=top;align=left;overflow=fill;fontSize=12;fontFamily=Helvetica;html=1;fillColor=#ffffff;strokeColor=#000000;" value="&lt;p style=&quot;margin: 0px ; margin-top: 4px ; text-align: center ; text-decoration: underline&quot;&gt;&lt;font style=&quot;font-size: 13px&quot;&gt;&lt;b&gt;vf:ProposedIntent&lt;/b&gt;&lt;br&gt;&lt;/font&gt;&lt;/p&gt;&lt;hr&gt;&lt;p style=&quot;margin: 0px ; margin-left: 8px&quot;&gt;&lt;font style=&quot;font-size: 11px&quot;&gt;vf:reciprocal&lt;/font&gt;&lt;/p&gt;" vertex="1">
          <mxGeometry height="60" width="150" x="1014" y="87" as="geometry" />
        </mxCell>
        <mxCell id="8f4O_Xt_eh_mQ_HBJD7Y-30" edge="1" parent="1" source="8f4O_Xt_eh_mQ_HBJD7Y-29" style="endArrow=classic;html=1;exitX=1;exitY=0.5;exitDx=0;exitDy=0;entryX=0;entryY=0.25;entryDx=0;entryDy=0;" target="8f4O_Xt_eh_mQ_HBJD7Y-28" value="vf:publishedIn">
          <mxGeometry height="50" relative="1" width="50" x="0.0498" y="-1" as="geometry">
            <mxPoint as="offset" />
            <mxPoint x="1022" y="32" as="sourcePoint" />
            <mxPoint x="976" y="27" as="targetPoint" />
          </mxGeometry>
        </mxCell>
        <mxCell id="8f4O_Xt_eh_mQ_HBJD7Y-31" edge="1" parent="1" source="8f4O_Xt_eh_mQ_HBJD7Y-29" style="endArrow=classic;html=1;exitX=0.5;exitY=1;exitDx=0;exitDy=0;entryX=0.5;entryY=0;entryDx=0;entryDy=0;" target="8f4O_Xt_eh_mQ_HBJD7Y-27" value="vf:publishes">
          <mxGeometry height="50" relative="1" width="50" as="geometry">
            <mxPoint x="922" y="132" as="sourcePoint" />
            <mxPoint x="989.3519999999999" y="154.73000000000002" as="targetPoint" />
          </mxGeometry>
        </mxCell>
        <mxCell id="8f4O_Xt_eh_mQ_HBJD7Y-32" parent="1" style="text;html=1;strokeColor=none;fillColor=none;align=center;verticalAlign=middle;whiteSpace=wrap;rounded=0;fontSize=16;" value="OLD" vertex="1">
          <mxGeometry height="30" width="60" x="1050" y="40" as="geometry" />
        </mxCell>
        <mxCell id="8f4O_Xt_eh_mQ_HBJD7Y-33" parent="1" style="text;html=1;strokeColor=none;fillColor=none;align=center;verticalAlign=middle;whiteSpace=wrap;rounded=0;" value="*" vertex="1">
          <mxGeometry height="20" width="20" x="239" y="260" as="geometry" />
        </mxCell>
        <mxCell id="8f4O_Xt_eh_mQ_HBJD7Y-34" parent="1" style="text;html=1;strokeColor=none;fillColor=none;align=center;verticalAlign=middle;whiteSpace=wrap;rounded=0;" value="*" vertex="1">
          <mxGeometry height="20" width="20" x="234" y="214" as="geometry" />
        </mxCell>
        <mxCell id="8f4O_Xt_eh_mQ_HBJD7Y-35" parent="1" style="text;html=1;strokeColor=none;fillColor=none;align=center;verticalAlign=middle;whiteSpace=wrap;rounded=0;" value="*" vertex="1">
          <mxGeometry height="20" width="20" x="609" y="288.5" as="geometry" />
        </mxCell>
        <mxCell id="8f4O_Xt_eh_mQ_HBJD7Y-36" parent="1" style="verticalAlign=top;align=left;overflow=fill;fontSize=12;fontFamily=Helvetica;html=1;fillColor=#ffffff;strokeColor=#000000;" value="&lt;p style=&quot;margin: 4px 0px 0px; text-align: center; text-decoration: underline;&quot;&gt;&lt;font style=&quot;font-size: 13px&quot;&gt;&lt;b&gt;Commitment&lt;/b&gt;&lt;br&gt;&lt;/font&gt;&lt;/p&gt;&lt;hr&gt;" vertex="1">
          <mxGeometry height="79" width="151" x="1360" y="830" as="geometry" />
        </mxCell>
        <mxCell id="8f4O_Xt_eh_mQ_HBJD7Y-37" parent="1" style="verticalAlign=top;align=left;overflow=fill;fontSize=12;fontFamily=Helvetica;html=1;fillColor=#ffffff;strokeColor=#000000;" value="&lt;p style=&quot;margin: 4px 0px 0px; text-align: center; text-decoration: underline;&quot;&gt;&lt;font style=&quot;font-size: 13px&quot;&gt;&lt;b&gt;EconomicEvent&lt;/b&gt;&lt;br&gt;&lt;/font&gt;&lt;/p&gt;&lt;hr&gt;" vertex="1">
          <mxGeometry height="70" width="151" x="1453" y="1191" as="geometry" />
        </mxCell>
        <mxCell id="8f4O_Xt_eh_mQ_HBJD7Y-38" parent="1" style="verticalAlign=top;align=left;overflow=fill;fontSize=12;fontFamily=Helvetica;html=1;fillColor=#eeeeee;strokeColor=#36393d;" value="&lt;p style=&quot;margin: 4px 0px 0px; text-align: center; text-decoration: underline;&quot;&gt;&lt;font style=&quot;font-size: 13px&quot;&gt;&lt;b&gt;Fulfillment&lt;/b&gt;&lt;br&gt;&lt;/font&gt;&lt;/p&gt;&lt;hr&gt;&lt;div&gt;&lt;font style=&quot;font-size: 11px&quot;&gt;&amp;nbsp;&lt;/font&gt;&lt;/div&gt;" vertex="1">
          <mxGeometry height="70" width="130" x="1390" y="991" as="geometry" />
        </mxCell>
        <mxCell id="8f4O_Xt_eh_mQ_HBJD7Y-39" edge="1" parent="1" source="8f4O_Xt_eh_mQ_HBJD7Y-38" style="endArrow=classic;endFill=1;endSize=6;html=1;strokeColor=#000000;exitX=0.5;exitY=1;entryX=0.116;entryY=-0.005;entryDx=0;entryDy=0;exitDx=0;exitDy=0;entryPerimeter=0;labelBackgroundColor=none;startArrow=classic;startFill=1;" target="8f4O_Xt_eh_mQ_HBJD7Y-37" value="fulfillment">
          <mxGeometry width="100" as="geometry">
            <mxPoint y="-38" as="offset" />
            <mxPoint x="1554.475308641975" y="1122.225308641975" as="sourcePoint" />
            <mxPoint x="1221" y="1252.067149504282" as="targetPoint" />
          </mxGeometry>
        </mxCell>
        <mxCell id="8f4O_Xt_eh_mQ_HBJD7Y-40" edge="1" parent="1" source="8f4O_Xt_eh_mQ_HBJD7Y-38" style="endArrow=block;endFill=1;endSize=6;html=1;strokeColor=#000000;exitX=0.5;exitY=0;entryX=0.5;entryY=1;exitDx=0;exitDy=0;entryDx=0;entryDy=0;labelBackgroundColor=none;" target="8f4O_Xt_eh_mQ_HBJD7Y-36" value="fulfills">
          <mxGeometry width="100" as="geometry">
            <mxPoint x="-9" y="-4" as="offset" />
            <Array as="points" />
            <mxPoint x="1903" y="1245" as="sourcePoint" />
            <mxPoint x="1997.8869891114505" y="944.5138772572416" as="targetPoint" />
          </mxGeometry>
        </mxCell>
        <mxCell id="8f4O_Xt_eh_mQ_HBJD7Y-41" parent="1" style="verticalAlign=top;align=left;overflow=fill;fontSize=12;fontFamily=Helvetica;html=1;fillColor=#ffffff;strokeColor=#000000;" value="&lt;p style=&quot;margin: 4px 0px 0px; text-align: center; text-decoration: underline;&quot;&gt;&lt;font style=&quot;font-size: 13px&quot;&gt;&lt;b&gt;Intent&lt;/b&gt;&lt;br&gt;&lt;/font&gt;&lt;/p&gt;&lt;hr&gt;&lt;br&gt;&lt;p style=&quot;margin: 0px ; margin-left: 8px&quot;&gt;&lt;font&gt;&lt;br&gt;&lt;/font&gt;&lt;/p&gt;" vertex="1">
          <mxGeometry height="75" width="120" x="884" y="830" as="geometry" />
        </mxCell>
        <mxCell id="8f4O_Xt_eh_mQ_HBJD7Y-42" parent="1" style="verticalAlign=top;align=left;overflow=fill;fontSize=12;fontFamily=Helvetica;html=1;fillColor=#eeeeee;strokeColor=#36393d;" value="&lt;p style=&quot;margin: 4px 0px 0px; text-align: center; text-decoration: underline;&quot;&gt;&lt;font style=&quot;font-size: 13px&quot;&gt;&lt;b&gt;Satisfaction&lt;/b&gt;&lt;br&gt;&lt;/font&gt;&lt;/p&gt;&lt;hr&gt;" vertex="1">
          <mxGeometry height="70" width="130" x="1100" y="830" as="geometry" />
        </mxCell>
        <mxCell id="8f4O_Xt_eh_mQ_HBJD7Y-43" edge="1" parent="1" source="8f4O_Xt_eh_mQ_HBJD7Y-42" style="endArrow=classic;html=1;exitX=1;exitY=0.5;entryX=0;entryY=0.25;entryDx=0;entryDy=0;labelBackgroundColor=none;startArrow=classic;startFill=1;endFill=1;" target="8f4O_Xt_eh_mQ_HBJD7Y-36" value=":satisfaction">
          <mxGeometry height="50" relative="1" width="50" x="-0.401" y="-9" as="geometry">
            <mxPoint x="1" as="offset" />
            <mxPoint x="1784" y="900" as="sourcePoint" />
            <mxPoint x="1834" y="850" as="targetPoint" />
          </mxGeometry>
        </mxCell>
        <mxCell id="8f4O_Xt_eh_mQ_HBJD7Y-44" edge="1" parent="1" source="8f4O_Xt_eh_mQ_HBJD7Y-42" style="endArrow=classic;html=1;exitX=0;exitY=0.5;entryX=1;entryY=0.5;labelBackgroundColor=none;" target="8f4O_Xt_eh_mQ_HBJD7Y-41" value="satisfies">
          <mxGeometry height="50" relative="1" width="50" x="0.2121" y="-5" as="geometry">
            <mxPoint as="offset" />
            <mxPoint x="1424" y="930" as="sourcePoint" />
            <mxPoint x="1474" y="880" as="targetPoint" />
          </mxGeometry>
        </mxCell>
        <mxCell id="8f4O_Xt_eh_mQ_HBJD7Y-45" edge="1" parent="1" source="8f4O_Xt_eh_mQ_HBJD7Y-42" style="endArrow=classic;html=1;exitX=0.5;exitY=1;entryX=0;entryY=0.25;entryDx=0;entryDy=0;exitDx=0;exitDy=0;labelBackgroundColor=none;startArrow=classic;startFill=1;endFill=1;" target="8f4O_Xt_eh_mQ_HBJD7Y-37" value="satisfaction">
          <mxGeometry height="50" relative="1" width="50" x="-0.8175" y="12" as="geometry">
            <mxPoint as="offset" />
            <mxPoint x="1929" y="875" as="sourcePoint" />
            <mxPoint x="2118" y="866" as="targetPoint" />
          </mxGeometry>
        </mxCell>
        <mxCell id="8f4O_Xt_eh_mQ_HBJD7Y-46" edge="1" parent="1" source="8f4O_Xt_eh_mQ_HBJD7Y-48" style="endArrow=classic;html=1;entryX=0.5;entryY=0;entryDx=0;entryDy=0;labelBackgroundColor=none;exitX=0.5;exitY=1;exitDx=0;exitDy=0;startArrow=classic;startFill=1;endFill=1;" target="8f4O_Xt_eh_mQ_HBJD7Y-37" value="settlement">
          <mxGeometry height="50" relative="1" width="50" x="-0.5173" y="3" as="geometry">
            <mxPoint y="1" as="offset" />
            <mxPoint x="1564" y="1131" as="sourcePoint" />
            <mxPoint x="1327" y="1929" as="targetPoint" />
          </mxGeometry>
        </mxCell>
        <mxCell id="8f4O_Xt_eh_mQ_HBJD7Y-47" edge="1" parent="1" source="8f4O_Xt_eh_mQ_HBJD7Y-48" style="endArrow=classic;html=1;entryX=0.25;entryY=1;entryDx=0;entryDy=0;labelBackgroundColor=none;exitX=0.75;exitY=0;exitDx=0;exitDy=0;" target="8f4O_Xt_eh_mQ_HBJD7Y-49" value="settles">
          <mxGeometry height="50" relative="1" width="50" x="0.0565" y="-2" as="geometry">
            <mxPoint y="1" as="offset" />
            <mxPoint x="1592" y="1051" as="sourcePoint" />
            <mxPoint x="1324" y="1751" as="targetPoint" />
          </mxGeometry>
        </mxCell>
        <mxCell id="8f4O_Xt_eh_mQ_HBJD7Y-48" parent="1" style="verticalAlign=top;align=left;overflow=fill;fontSize=12;fontFamily=Helvetica;html=1;fillColor=#eeeeee;strokeColor=#36393d;" value="&lt;p style=&quot;margin: 4px 0px 0px; text-align: center; text-decoration: underline;&quot;&gt;&lt;font style=&quot;font-size: 13px&quot;&gt;&lt;b&gt;Settlement&lt;/b&gt;&lt;br&gt;&lt;/font&gt;&lt;/p&gt;&lt;hr&gt;&lt;div&gt;&lt;font style=&quot;font-size: 11px&quot;&gt;&amp;nbsp;&lt;/font&gt;&lt;/div&gt;" vertex="1">
          <mxGeometry height="70" width="111" x="1551" y="1031" as="geometry" />
        </mxCell>
        <mxCell id="8f4O_Xt_eh_mQ_HBJD7Y-49" parent="1" style="verticalAlign=top;align=left;overflow=fill;fontSize=12;fontFamily=Helvetica;html=1;fillColor=#ffffff;strokeColor=#000000;" value="&lt;p style=&quot;margin: 4px 0px 0px; text-align: center; text-decoration: underline;&quot;&gt;&lt;font style=&quot;font-size: 13px&quot;&gt;&lt;b&gt;Claim&lt;/b&gt;&lt;br&gt;&lt;/font&gt;&lt;/p&gt;&lt;hr&gt;" vertex="1">
          <mxGeometry height="71" width="120" x="1680" y="881" as="geometry" />
        </mxCell>
        <mxCell id="8f4O_Xt_eh_mQ_HBJD7Y-51" parent="1" style="text;html=1;strokeColor=none;fillColor=none;align=center;verticalAlign=middle;whiteSpace=wrap;rounded=0;" value="satisfiedBy" vertex="1">
          <mxGeometry height="30" width="90" x="1371" y="1171" as="geometry" />
        </mxCell>
        <mxCell id="8f4O_Xt_eh_mQ_HBJD7Y-52" parent="1" style="text;html=1;strokeColor=none;fillColor=none;align=center;verticalAlign=middle;whiteSpace=wrap;rounded=0;" value="satisfiedBy" vertex="1">
          <mxGeometry height="30" width="90" x="1270" y="826" as="geometry" />
        </mxCell>
        <mxCell id="8f4O_Xt_eh_mQ_HBJD7Y-53" parent="1" style="text;html=1;strokeColor=none;fillColor=none;align=center;verticalAlign=middle;whiteSpace=wrap;rounded=0;" value="*" vertex="1">
          <mxGeometry height="20" width="25" x="1450" y="1070" as="geometry" />
        </mxCell>
        <mxCell id="8f4O_Xt_eh_mQ_HBJD7Y-54" parent="1" style="text;html=1;strokeColor=none;fillColor=none;align=center;verticalAlign=middle;whiteSpace=wrap;rounded=0;" value="*" vertex="1">
          <mxGeometry height="20" width="25" x="1600" y="1110" as="geometry" />
        </mxCell>
        <mxCell id="8f4O_Xt_eh_mQ_HBJD7Y-55" parent="1" style="text;html=1;strokeColor=none;fillColor=none;align=center;verticalAlign=middle;whiteSpace=wrap;rounded=0;" value="fulfilledBy" vertex="1">
          <mxGeometry height="30" width="84" x="1427" y="1148" as="geometry" />
        </mxCell>
        <mxCell id="8f4O_Xt_eh_mQ_HBJD7Y-56" parent="1" style="text;html=1;strokeColor=none;fillColor=none;align=center;verticalAlign=middle;whiteSpace=wrap;rounded=0;" value="settledBy" vertex="1">
          <mxGeometry height="30" width="70" x="1520" y="1156" as="geometry" />
        </mxCell>
        <mxCell id="Cy4T0XdHyobR2D_hUTC2-2" parent="1" style="text;html=1;strokeColor=none;fillColor=none;align=center;verticalAlign=middle;whiteSpace=wrap;rounded=0;" value="*" vertex="1">
          <mxGeometry height="20" width="25" x="1149" y="900" as="geometry" />
        </mxCell>
        <mxCell id="Cy4T0XdHyobR2D_hUTC2-3" parent="1" style="text;html=1;strokeColor=none;fillColor=none;align=center;verticalAlign=middle;whiteSpace=wrap;rounded=0;" value="*" vertex="1">
          <mxGeometry height="20" width="25" x="1224" y="848" as="geometry" />
        </mxCell>
        <mxCell id="Cy4T0XdHyobR2D_hUTC2-4" parent="1" style="text;html=1;strokeColor=none;fillColor=none;align=center;verticalAlign=middle;whiteSpace=wrap;rounded=0;fontSize=16;" value="OLD" vertex="1">
          <mxGeometry height="30" width="60" x="1080" y="760" as="geometry" />
        </mxCell>
      </root>
    </mxGraphModel>
  </diagram>
</mxfile>
