<?xml version="1.0" encoding="UTF-8"?>
<mxfile modified="2019-08-07T16:12:55.231Z" host="www.draw.io" agent="Mozilla/5.0 (X11; Ubuntu; Linux x86_64; rv:68.0) Gecko/20100101 Firefox/68.0" version="11.1.1" etag="vX_keMs7XRLeBlwbk2Ri" type="device" compressed="false">
  <diagram id="q-BsAQJefdVYjLElGB8P">
    <mxGraphModel dx="1355" dy="778" grid="1" gridSize="10" guides="1" tooltips="1" connect="1" arrows="1" fold="1" page="1" pageScale="1" pageWidth="850" pageHeight="1100" math="0" shadow="0">
      <root>
        <mxCell id="0"/>
        <mxCell id="1" parent="0"/>
        <mxCell id="2" value="" style="rounded=0;whiteSpace=wrap;html=1;fillColor=#fad9d5;strokeColor=none;align=left;verticalAlign=top;" vertex="1" parent="1">
          <mxGeometry x="20" y="1050" width="610" height="130" as="geometry"/>
        </mxCell>
        <mxCell id="3" value="" style="rounded=0;whiteSpace=wrap;html=1;fillColor=#d5e8d4;strokeColor=none;align=left;verticalAlign=top;" vertex="1" parent="1">
          <mxGeometry x="20" y="1180" width="610" height="70" as="geometry"/>
        </mxCell>
        <mxCell id="4" value="Carol&#39;s bank account" style="rounded=0;whiteSpace=wrap;html=1;" vertex="1" parent="1">
          <mxGeometry x="375" y="1196" width="85" height="40" as="geometry"/>
        </mxCell>
        <mxCell id="5" value="" style="endArrow=classic;html=1;exitX=1;exitY=0.5;exitDx=0;exitDy=0;entryX=0;entryY=0.5;entryDx=0;entryDy=0;" edge="1" source="4" target="6" parent="1">
          <mxGeometry width="50" height="50" relative="1" as="geometry">
            <mxPoint x="476" y="1216" as="sourcePoint"/>
            <mxPoint x="521.5" y="1286" as="targetPoint"/>
          </mxGeometry>
        </mxCell>
        <mxCell id="6" value="transfer $5 to the store" style="shape=delay;whiteSpace=wrap;html=1;rounded=0;glass=1;comic=0;" vertex="1" parent="1">
          <mxGeometry x="480.5" y="1196" width="97" height="40" as="geometry"/>
        </mxCell>
        <mxCell id="7" value="transfer 1 bucket to Carol" style="shape=delay;whiteSpace=wrap;html=1;rounded=0;glass=1;comic=0;" vertex="1" parent="1">
          <mxGeometry x="260" y="1196" width="103" height="40" as="geometry"/>
        </mxCell>
        <mxCell id="8" value="Agreement" style="shape=hexagon;perimeter=hexagonPerimeter2;whiteSpace=wrap;html=1;" vertex="1" parent="1">
          <mxGeometry x="114" y="1060" width="100" height="40" as="geometry"/>
        </mxCell>
        <mxCell id="9" value="Agreement" style="shape=hexagon;perimeter=hexagonPerimeter2;whiteSpace=wrap;html=1;" vertex="1" parent="1">
          <mxGeometry x="364.5" y="1060" width="100" height="40" as="geometry"/>
        </mxCell>
        <mxCell id="10" value="commit to transfer 50kg apples to Bob" style="shape=delay;whiteSpace=wrap;html=1;rounded=0;glass=1;comic=0;" vertex="1" parent="1">
          <mxGeometry x="30" y="1120" width="129" height="40" as="geometry"/>
        </mxCell>
        <mxCell id="11" value="" style="endArrow=classic;html=1;exitX=0.75;exitY=0;exitDx=0;exitDy=0;entryX=0.375;entryY=1;entryDx=0;entryDy=0;" edge="1" source="10" target="8" parent="1">
          <mxGeometry width="50" height="50" relative="1" as="geometry">
            <mxPoint x="70" y="1120" as="sourcePoint"/>
            <mxPoint x="120" y="1070" as="targetPoint"/>
          </mxGeometry>
        </mxCell>
        <mxCell id="12" value="commit to transfer 10L cider to Alice" style="shape=delay;whiteSpace=wrap;html=1;rounded=0;glass=1;comic=0;" vertex="1" parent="1">
          <mxGeometry x="172" y="1120" width="118" height="40" as="geometry"/>
        </mxCell>
        <mxCell id="13" value="" style="endArrow=classic;html=1;exitX=0.625;exitY=1;exitDx=0;exitDy=0;entryX=0.25;entryY=0;entryDx=0;entryDy=0;" edge="1" source="8" target="12" parent="1">
          <mxGeometry width="50" height="50" relative="1" as="geometry">
            <mxPoint x="94.5" y="1130" as="sourcePoint"/>
            <mxPoint x="195" y="1100" as="targetPoint"/>
          </mxGeometry>
        </mxCell>
        <mxCell id="14" value="" style="endArrow=classic;html=1;exitX=0.5;exitY=0;exitDx=0;exitDy=0;entryX=0.375;entryY=1;entryDx=0;entryDy=0;" edge="1" source="7" target="9" parent="1">
          <mxGeometry width="50" height="50" relative="1" as="geometry">
            <mxPoint x="370" y="1190" as="sourcePoint"/>
            <mxPoint x="420" y="1140" as="targetPoint"/>
          </mxGeometry>
        </mxCell>
        <mxCell id="15" value="" style="endArrow=classic;html=1;exitX=0.625;exitY=1;exitDx=0;exitDy=0;entryX=0.5;entryY=0;entryDx=0;entryDy=0;" edge="1" source="9" target="6" parent="1">
          <mxGeometry width="50" height="50" relative="1" as="geometry">
            <mxPoint x="460" y="1180" as="sourcePoint"/>
            <mxPoint x="510" y="1130" as="targetPoint"/>
          </mxGeometry>
        </mxCell>
      </root>
    </mxGraphModel>
  </diagram>
</mxfile>
